olive2022.py
olive2022-0.1.7.dist-info/entry_points.txt
olive2022-0.1.7.dist-info/LICENSE
olive2022-0.1.7.dist-info/WHEEL
olive2022-0.1.7.dist-info/METADATA
olive2022-0.1.7.dist-info/RECORD
