Metadata-Version: 2.1
Name: olive2022
Version: 0.1.7
Summary: Edge-native virtual desktop application
Home-page: https://github.com/cmusatyalab/olive2022
License: MIT
Author: Carnegie Mellon University
Author-email: satya+group@cs.cmu.edu
Requires-Python: >=3.7,<4.0
Classifier: Development Status :: 4 - Beta
Classifier: Environment :: Console
Classifier: Environment :: X11 Applications
Classifier: Intended Audience :: End Users/Desktop
Classifier: License :: OSI Approved :: MIT License
Classifier: Programming Language :: Python :: 3
Classifier: Programming Language :: Python :: 3.7
Classifier: Programming Language :: Python :: 3.8
Classifier: Programming Language :: Python :: 3.9
Classifier: Programming Language :: Python :: 3.10
Classifier: Programming Language :: Python :: 3.11
Requires-Dist: pyyaml (>=6.0,<7.0)
Requires-Dist: sinfonia-tier3 (>=0.7.0,<0.8.0)
Requires-Dist: tqdm (>=4.64.1,<5.0.0)
Requires-Dist: xdg (>=5.1.1,<6.0.0)
Requires-Dist: yarl (>=1.8.1,<2.0.0)
Project-URL: Repository, https://github.com/cmusatyalab/olive2022
